CHANGES.txt
README.txt
buildout.cfg
setup.py
bootstrap/bootstrap.py
src/zc/__init__.py
src/zc.dict.egg-info/PKG-INFO
src/zc.dict.egg-info/SOURCES.txt
src/zc.dict.egg-info/dependency_links.txt
src/zc.dict.egg-info/namespace_packages.txt
src/zc.dict.egg-info/not-zip-safe
src/zc.dict.egg-info/requires.txt
src/zc.dict.egg-info/top_level.txt
src/zc/dict/__init__.py
src/zc/dict/dict.py
src/zc/dict/dict.txt
src/zc/dict/ordered.py
src/zc/dict/ordered.txt
src/zc/dict/tests.py
