Metadata-Version: 1.0
Name: zc.dict
Version: 1.2
Summary: BTree-based persistent dict-like objects (regular dict and ordered) that can be
